ediq.py
ediq-2.0.0.dist-info/licenses/LICENSE
ediq-2.0.0.dist-info/METADATA
ediq-2.0.0.dist-info/WHEEL
ediq-2.0.0.dist-info/top_level.txt
ediq-2.0.0.dist-info/RECORD
